shift_reg/Rshift/rshift.v
module rightshiftreg (in,clk,rst,out);

input wire  in;
input wire clk;
input wire rst;

output reg  [3:0] out;

always @(posedge clk) begin
    if(rst)

    out=4'b0000;

    else begin

    out ={in,out[3:1]};


    end
    
end
    
 endmodule

shift_reg/Rshift/rshift_tb.v
module rightshiftreg_tb;

    reg in_tb;
    reg clk;
    reg rst;
    wire [3:0] out_tb;

    always #5 clk = ~clk;

    initial begin
        clk = 0;
        rst = 1;
        #10;
        rst = 0;
        in_tb = 1'b 1;
        #10
        in_tb = 1'b0;
        #10
        in_tb = 1'b1;
        #10
        in_tb = 1'b0;
        #10


        $finish;
    end

    rightshiftreg u_shiftut (
        .in(in_tb),
        .clk(clk),
        .rst(rst),
        .out(out_tb)
    );

    initial begin
        $dumpfile("rightshiftreg.vcd");
        $dumpvars(0, rightshiftreg_tb);
    end
endmodule

shift_reg/Rshift/rightshiftreg.vcd
$date
	Wed Aug  9 13:03:42 2023
$end
$version
	Icarus Verilog
$end
$timescale
	1s
$end
$scope module rightshiftreg_tb $end
$var wire 4 ! out_tb [3:0] $end
$var reg 1 " clk $end
$var reg 1 # in_tb $end
$var reg 1 $ rst $end
$scope module u_shiftut $end
$var wire 1 " clk $end
$var wire 1 # in $end
$var wire 1 $ rst $end
$var reg 4 % out [3:0] $end
$upscope $end
$upscope $end
$enddefinitions $end
#0
$dumpvars
bx %
1$
x#
0"
bx !
$end
#5
b0 !
b0 %
1"
#10
0"
1#
0$
#15
b1000 !
b1000 %
1"
#20
0"
0#
#25
b100 !
b100 %
1"
#30
0"
1#
#35
b1010 !
b1010 %
1"
#40
0"
0#
#45
b101 !
b101 %
1"
