shift_reg/Lshift/lshift.v
module leftshiftreg (in,clk,rst,out);

input wire in;
input wire clk;
input wire rst;

output reg  [3:0] out;

always @(posedge clk) begin
    if(rst)

    out=4'b0000;

    else begin

    out ={out[2:0],in};


    end
    
end
    
 endmodule

shift_reg/Lshift/lshift_tb.v
`timescale 1ns/1ps
module leftshiftreg_tb;

    reg  in_tb;
    reg clk;
    reg rst;
    wire [3:0] out_tb;

    always #5 clk = ~clk;

    initial begin
        clk = 0;
        rst = 1;
        #10;
        rst = 0;
        in_tb = 1'b 1;
        #10
        in_tb = 1'b0;
        #10
        in_tb = 1'b1;
        #10
        in_tb = 1'b0;
        #10



        
        $finish;
    end

    leftshiftreg u_Lshift (
        .in(in_tb),
        .clk(clk),
        .rst(rst),
        .out(out_tb)
    );

    initial begin
        $dumpfile("leftshiftreg.vcd");
        $dumpvars(0, leftshiftreg_tb);
    end
endmodule

shift_reg/Lshift/leftshiftreg.vcd
$date
	Wed Aug  9 12:52:40 2023
$end
$version
	Icarus Verilog
$end
$timescale
	1ps
$end
$scope module leftshiftreg_tb $end
$var wire 4 ! out_tb [3:0] $end
$var reg 1 " clk $end
$var reg 1 # in_tb $end
$var reg 1 $ rst $end
$scope module u_Lshift $end
$var wire 1 " clk $end
$var wire 1 # in $end
$var wire 1 $ rst $end
$var reg 4 % out [3:0] $end
$upscope $end
$upscope $end
$enddefinitions $end
#0
$dumpvars
bx %
1$
x#
0"
bx !
$end
#5000
b0 !
b0 %
1"
#10000
0"
1#
0$
#15000
b1 !
b1 %
1"
#20000
0"
0#
#25000
b10 !
b10 %
1"
#30000
0"
1#
#35000
b101 !
b101 %
1"
#40000
0"
0#
#45000
b1010 !
b1010 %
1"
