FA/fa.v
`timescale 1ns/1ps
module fa (a,b,cin,sum,cout);
 input wire a;
 input wire b;
 input wire cin;
 output wire sum ;
 output wire cout;

 wire s0;
 wire c1;
 wire c0;

 assign s0 = a^b;
 assign c1 = s0&cin;
 assign c0 =a&b;
 assign sum = s0^cin;
 assign cout = c1|c0;

    
endmodule

FA/fa_tb.v
`timescale 1ns/1ps
module fa_tb ();

reg a_tb;
reg b_tb;
reg cin_tb;
wire sum_tb,cout_tb;

initial begin
    a_tb=0; b_tb=0; cin_tb=0;
    #1;
    a_tb=0; b_tb=0; cin_tb=1;
    #1;
     a_tb=0; b_tb=1; cin_tb=0;
    #1;
     a_tb=0; b_tb=1; cin_tb=1;
    #1;
     a_tb=1; b_tb=0; cin_tb=0;
    #1;
     a_tb=1; b_tb=0; cin_tb=1;
    #1;
     a_tb=1; b_tb=1; cin_tb=0;
    #1;
     a_tb=1; b_tb=1; cin_tb=1;
    

    $display ("sum_tb value is %d",sum_tb);
    $display ("cout_tb value is %d",cout_tb);
    #3;
end
fa u_fa0
(
    .a(a_tb),
    .b(b_tb),
    .cin(cin_tb),
    .sum(sum_tb),
    .cout(cout_tb)
);
initial begin
    $dumpfile("fa.vcd");
    $dumpvars(0,fa_tb);
end
    
endmodule

FA/fa.vcd
$date
	Thu Aug  3 16:13:22 2023
$end
$version
	Icarus Verilog
$end
$timescale
	1ps
$end
$scope module fa_tb $end
$var wire 1 ! sum_tb $end
$var wire 1 " cout_tb $end
$var reg 1 # a_tb $end
$var reg 1 $ b_tb $end
$var reg 1 % cin_tb $end
$scope module u_fa0 $end
$var wire 1 # a $end
$var wire 1 $ b $end
$var wire 1 & c0 $end
$var wire 1 ' c1 $end
$var wire 1 % cin $end
$var wire 1 " cout $end
$var wire 1 ( s0 $end
$var wire 1 ! sum $end
$upscope $end
$upscope $end
$enddefinitions $end
#0
$dumpvars
0(
0'
0&
0%
0$
0#
0"
0!
$end
#1000
1!
1%
#2000
1(
0%
1$
#3000
1"
1'
0!
1%
#4000
0"
0'
1!
0%
0$
1#
#5000
1"
1'
0!
1%
#6000
0'
0(
1&
0%
1$
#7000
1!
1%
