ALu/alu.v
module alu ( a_i, b_i, op_i, res_o);
input wire [7:0]a_i;
input wire [7:0]b_i;
input wire [2:0]op_i;
output reg [7:0]res_o;

always @(*)
begin
    if(op_i == 3'b000) begin
    res_o = a_i+b_i; 
    end
    else if(op_i == 3'b001) begin
    res_o = a_i-b_i;
    end
    else if(op_i == 3'b010) begin
    res_o = a_i&b_i;
    end
    else if(op_i == 3'b011) begin
    res_o = a_i|b_i;
    end
    else if(op_i == 3'b100) begin
    res_o = a_i^b_i;
    end
    else if(op_i == 3'b101) begin
    res_o = a_i<<b_i;
    end
    else if(op_i == 3'b110) begin
    res_o = a_i>>b_i;
    end
    else  begin
    res_o = 0;
    end

end


    
endmodule

Alu/alu_tb.v
`timescale 1ns/1ps
module alu_tb ();
 reg [7:0]a_tb;
 reg [7:0]b_tb;
 reg [2:0]op_tb;
 wire [7:0]res_tb;
 integer i;

 initial begin
    a_tb= 10;
    b_tb=3;
    for ( i=0; i<7; i++) begin
        op_tb=i;
        #1;
         $display ("res_tb value is %d",res_tb);
    #1;
    end
    


  

     end
     alu u_alu0
     (
        .a_i(a_tb),
        .b_i(b_tb),
        .op_i(op_tb),
        .res_o(res_tb)
     );
initial begin
    $dumpfile("alu.vcd");
    $dumpvars(0,alu_tb);
end
    
endmodule

Alu/alu.vcd
$date
	Mon Aug  7 15:29:54 2023
$end
$version
	Icarus Verilog
$end
$timescale
	1ps
$end
$scope module alu_tb $end
$var wire 8 ! res_tb [7:0] $end
$var reg 8 " a_tb [7:0] $end
$var reg 8 # b_tb [7:0] $end
$var reg 3 $ op_tb [2:0] $end
$var integer 32 % i [31:0] $end
$scope module u_alu0 $end
$var wire 8 & a_i [7:0] $end
$var wire 8 ' b_i [7:0] $end
$var wire 3 ( op_i [2:0] $end
$var reg 8 ) res_o [7:0] $end
$upscope $end
$upscope $end
$enddefinitions $end
#0
$dumpvars
b1101 )
b0 (
b11 '
b1010 &
b0 %
b0 $
b11 #
b1010 "
b1101 !
$end
#2000
b111 !
b111 )
b1 $
b1 (
b1 %
#4000
b10 !
b10 )
b10 $
b10 (
b10 %
#6000
b1011 !
b1011 )
b11 $
b11 (
b11 %
#8000
b1001 !
b1001 )
b100 $
b100 (
b100 %
#10000
b1010000 !
b1010000 )
b101 $
b101 (
b101 %
#12000
b1 !
b1 )
b110 $
b110 (
b110 %
#14000
b111 %
